Metadata-Version: 2.1
Name: nb_probability
Version: 0.1.0
Summary: A package for Gaussian and Binomial distributions
Author: Coskun Erden
Classifier: Programming Language :: Python :: 3
Classifier: License :: OSI Approved :: MIT License
Classifier: Operating System :: OS Independent
Requires-Python: >=3.6
License-File: License.txt
Requires-Dist: matplotlib
Provides-Extra: dev
Requires-Dist: pytest; extra == "dev"
Requires-Dist: sphinx; extra == "dev"
